spring_py/__init__.py
spring_py/annotation.py
spring_py/application.py
spring_py/cli.py
spring_py/container.py
spring_py/context.py
spring_py/global_context.py
spring_py/scanner.py
spring_py_core-0.1.5.dist-info/METADATA
spring_py_core-0.1.5.dist-info/WHEEL
spring_py_core-0.1.5.dist-info/entry_points.txt
spring_py_core-0.1.5.dist-info/RECORD
