Metadata-Version: 2.4
Name: spring-py-core
Version: 0.1.5
Summary: A Python implementation of Spring Framework IoC container
Author-email: eee <eee1653545106@gmail.com>
Keywords: dependency-injection,framework,ioc,spring
Classifier: Development Status :: 3 - Alpha
Classifier: Intended Audience :: Developers
Classifier: License :: OSI Approved :: MIT License
Classifier: Programming Language :: Python :: 3
Classifier: Programming Language :: Python :: 3.11
Classifier: Programming Language :: Python :: 3.12
Requires-Python: >=3.11
Provides-Extra: cli
Requires-Dist: fastapi>=0.104.0; extra == 'cli'
Requires-Dist: uvicorn>=0.24.0; extra == 'cli'
Provides-Extra: dev
Requires-Dist: black>=23.0; extra == 'dev'
Requires-Dist: flake8>=6.0; extra == 'dev'
Requires-Dist: pytest-cov>=4.0; extra == 'dev'
Requires-Dist: pytest>=7.0; extra == 'dev'
